{
  "description": "London-only, Grade A only. Best proxy for deployed edge after forensics 2026-05-18.",
  "filter_note": "A+ excluded (13% WR, commitment failures). A = 41% WR, avg+0.840R.",
  "stats": {
    "n_trades": 39,
    "win_rate": 0.4103,
    "avg_r": 0.8397,
    "avg_win_r": 3.4844,
    "avg_loss_r": -1.0
  },
  "trades": [
    {
      "pair": "GBPUSD",
      "direction": "LONG",
      "grade": "A",
      "score": 7.99,
      "session": "London",
      "entry_dt": "2023-08-18 02:00",
      "entry": 1.27559,
      "stop": 1.27117,
      "tp1": 1.28886,
      "tp2": 1.30213,
      "atr": 0.00137,
      "outcome": "STOP",
      "exit_price": 1.27422,
      "pnl_r": -1.0,
      "hold_bars": 2,
      "component_scores": {
        "kill_zone": 2.0,
        "sweep": 1.988383098626515,
        "displacement": 2.0,
        "fvg_tap": 0.0,
        "market_structure": 2.0,
        "pd_alignment": 0.0
      }
    },
    {
      "pair": "GBPUSD",
      "direction": "LONG",
      "grade": "A",
      "score": 8.09,
      "session": "London",
      "entry_dt": "2023-08-21 03:00",
      "entry": 1.27205,
      "stop": 1.27009,
      "tp1": 1.27794,
      "tp2": 1.28382,
      "atr": 0.00128,
      "outcome": "TP2",
      "exit_price": 1.27717,
      "pnl_r": 4.5,
      "hold_bars": 17,
      "component_scores": {
        "kill_zone": 2.0,
        "sweep": 2.0857649645248326,
        "displacement": 2.0,
        "fvg_tap": 2.0,
        "market_structure": 0.0,
        "pd_alignment": 0.0
      }
    },
    {
      "pair": "GBPUSD",
      "direction": "LONG",
      "grade": "A",
      "score": 7.5,
      "session": "London",
      "entry_dt": "2023-08-29 04:00",
      "entry": 1.26205,
      "stop": 1.25634,
      "tp1": 1.27919,
      "tp2": 1.29633,
      "atr": 0.00085,
      "outcome": "STOP",
      "exit_price": 1.2612,
      "pnl_r": -1.0,
      "hold_bars": 1,
      "component_scores": {
        "kill_zone": 2.0,
        "sweep": 1.903306191211568,
        "displacement": 0.0,
        "fvg_tap": 2.0,
        "market_structure": 1.6,
        "pd_alignment": 0.0
      }
    },
    {
      "pair": "GBPUSD",
      "direction": "SHORT",
      "grade": "A",
      "score": 7.88,
      "session": "London",
      "entry_dt": "2023-09-13 02:00",
      "entry": 1.24934,
      "stop": 1.25448,
      "tp1": 1.23395,
      "tp2": 1.21856,
      "atr": 0.00107,
      "outcome": "TP2",
      "exit_price": 1.24508,
      "pnl_r": 4.5,
      "hold_bars": 2,
      "component_scores": {
        "kill_zone": 2.0,
        "sweep": 1.8774337025847598,
        "displacement": 0.0,
        "fvg_tap": 2.0,
        "market_structure": 2.0,
        "pd_alignment": 0.0
      }
    },
    {
      "pair": "GBPUSD",
      "direction": "LONG",
      "grade": "A",
      "score": 7.9,
      "session": "London",
      "entry_dt": "2023-09-14 03:00",
      "entry": 1.2498,
      "stop": 1.24467,
      "tp1": 1.26519,
      "tp2": 1.28058,
      "atr": 0.00112,
      "outcome": "STOP",
      "exit_price": 1.24868,
      "pnl_r": -1.0,
      "hold_bars": 3,
      "component_scores": {
        "kill_zone": 2.0,
        "sweep": 1.9007935297973868,
        "displacement": 2.0,
        "fvg_tap": 0.0,
        "market_structure": 2.0,
        "pd_alignment": 0.0
      }
    },
    {
      "pair": "GBPUSD",
      "direction": "SHORT",
      "grade": "A",
      "score": 7.96,
      "session": "London",
      "entry_dt": "2023-09-20 03:00",
      "entry": 1.23864,
      "stop": 1.24122,
      "tp1": 1.23088,
      "tp2": 1.22312,
      "atr": 0.00081,
      "outcome": "STOP",
      "exit_price": 1.23945,
      "pnl_r": -1.0,
      "hold_bars": 1,
      "component_scores": {
        "kill_zone": 2.0,
        "sweep": 2.3626936754539636,
        "displacement": 2.0,
        "fvg_tap": 0.0,
        "market_structure": 1.6,
        "pd_alignment": 0.0
      }
    },
    {
      "pair": "GBPUSD",
      "direction": "LONG",
      "grade": "A",
      "score": 8.49,
      "session": "London",
      "entry_dt": "2023-10-05 02:00",
      "entry": 1.2146,
      "stop": 1.20523,
      "tp1": 1.24273,
      "tp2": 1.27085,
      "atr": 0.00179,
      "outcome": "STOP",
      "exit_price": 1.21281,
      "pnl_r": -1.0,
      "hold_bars": 2,
      "component_scores": {
        "kill_zone": 2.0,
        "sweep": 1.989752318012847,
        "displacement": 2.0,
        "fvg_tap": 0.5,
        "market_structure": 2.0,
        "pd_alignment": 0.0
      }
    },
    {
      "pair": "GBPUSD",
      "direction": "LONG",
      "grade": "A",
      "score": 7.62,
      "session": "London",
      "entry_dt": "2023-10-09 03:00",
      "entry": 1.21841,
      "stop": 1.21147,
      "tp1": 1.23925,
      "tp2": 1.26009,
      "atr": 0.0023,
      "outcome": "TP1",
      "exit_price": 1.22302,
      "pnl_r": 1.25,
      "hold_bars": 20,
      "component_scores": {
        "kill_zone": 2.0,
        "sweep": 1.8790557035064357,
        "displacement": 1.742,
        "fvg_tap": 2.0,
        "market_structure": 0.0,
        "pd_alignment": 0.0
      }
    },
    {
      "pair": "GBPUSD",
      "direction": "LONG",
      "grade": "A",
      "score": 7.63,
      "session": "London",
      "entry_dt": "2023-10-23 02:00",
      "entry": 1.2151,
      "stop": 1.21038,
      "tp1": 1.22925,
      "tp2": 1.24341,
      "atr": 0.00125,
      "outcome": "TP2",
      "exit_price": 1.22011,
      "pnl_r": 4.5,
      "hold_bars": 11,
      "component_scores": {
        "kill_zone": 2.0,
        "sweep": 2.0346134256901296,
        "displacement": 2.0,
        "fvg_tap": 0.0,
        "market_structure": 1.6,
        "pd_alignment": 0.0
      }
    },
    {
      "pair": "GBPUSD",
      "direction": "LONG",
      "grade": "A",
      "score": 7.39,
      "session": "London",
      "entry_dt": "2023-11-02 02:00",
      "entry": 1.21847,
      "stop": 1.21266,
      "tp1": 1.23592,
      "tp2": 1.25338,
      "atr": 0.00196,
      "outcome": "STOP",
      "exit_price": 1.21651,
      "pnl_r": -1.0,
      "hold_bars": 4,
      "component_scores": {
        "kill_zone": 2.0,
        "sweep": 1.8988037675792175,
        "displacement": 1.492,
        "fvg_tap": 2.0,
        "market_structure": 0.0,
        "pd_alignment": 0.0
      }
    },
    {
      "pair": "GBPUSD",
      "direction": "SHORT",
      "grade": "A",
      "score": 7.96,
      "session": "London",
      "entry_dt": "2023-11-10 04:00",
      "entry": 1.22317,
      "stop": 1.2302,
      "tp1": 1.20211,
      "tp2": 1.18104,
      "atr": 0.00137,
      "outcome": "TP1",
      "exit_price": 1.22044,
      "pnl_r": 1.25,
      "hold_bars": 20,
      "component_scores": {
        "kill_zone": 2.0,
        "sweep": 1.9578129090161176,
        "displacement": 2.0,
        "fvg_tap": 2.0,
        "market_structure": 0.0,
        "pd_alignment": 0.0
      }
    },
    {
      "pair": "GBPUSD",
      "direction": "LONG",
      "grade": "A",
      "score": 7.95,
      "session": "London",
      "entry_dt": "2023-11-21 03:00",
      "entry": 1.2529,
      "stop": 1.23817,
      "tp1": 1.29707,
      "tp2": 1.34125,
      "atr": 0.00138,
      "outcome": "TP1",
      "exit_price": 1.25566,
      "pnl_r": 1.25,
      "hold_bars": 20,
      "component_scores": {
        "kill_zone": 2.0,
        "sweep": 1.9455434407435712,
        "displacement": 2.0,
        "fvg_tap": 2.0,
        "market_structure": 0.0,
        "pd_alignment": 0.0
      }
    },
    {
      "pair": "GBPUSD",
      "direction": "LONG",
      "grade": "A",
      "score": 8.04,
      "session": "London",
      "entry_dt": "2023-11-24 05:00",
      "entry": 1.25397,
      "stop": 1.25182,
      "tp1": 1.26042,
      "tp2": 1.26688,
      "atr": 0.00068,
      "outcome": "STOP",
      "exit_price": 1.25329,
      "pnl_r": -1.0,
      "hold_bars": 1,
      "component_scores": {
        "kill_zone": 2.0,
        "sweep": 2.0431175632436753,
        "displacement": 2.0,
        "fvg_tap": 2.0,
        "market_structure": 0.0,
        "pd_alignment": 0.0
      }
    },
    {
      "pair": "GBPUSD",
      "direction": "LONG",
      "grade": "A",
      "score": 7.26,
      "session": "London",
      "entry_dt": "2023-11-30 02:00",
      "entry": 1.27044,
      "stop": 1.26741,
      "tp1": 1.27953,
      "tp2": 1.28863,
      "atr": 0.00186,
      "outcome": "STOP",
      "exit_price": 1.26858,
      "pnl_r": -1.0,
      "hold_bars": 4,
      "component_scores": {
        "kill_zone": 2.0,
        "sweep": 1.9440602617930351,
        "displacement": 1.712,
        "fvg_tap": 0.0,
        "market_structure": 1.6,
        "pd_alignment": 0.0
      }
    },
    {
      "pair": "GBPUSD",
      "direction": "SHORT",
      "grade": "A",
      "score": 8.4,
      "session": "London",
      "entry_dt": "2023-12-07 02:00",
      "entry": 1.25649,
      "stop": 1.26464,
      "tp1": 1.23203,
      "tp2": 1.20757,
      "atr": 0.00121,
      "outcome": "STOP",
      "exit_price": 1.2577,
      "pnl_r": -1.0,
      "hold_bars": 1,
      "component_scores": {
        "kill_zone": 2.0,
        "sweep": 1.8981537296903257,
        "displacement": 2.0,
        "fvg_tap": 0.5,
        "market_structure": 2.0,
        "pd_alignment": 0.0
      }
    },
    {
      "pair": "GBPUSD",
      "direction": "LONG",
      "grade": "A",
      "score": 7.93,
      "session": "London",
      "entry_dt": "2024-01-04 04:00",
      "entry": 1.26673,
      "stop": 1.2622,
      "tp1": 1.28032,
      "tp2": 1.29391,
      "atr": 0.00137,
      "outcome": "TP2",
      "exit_price": 1.2722,
      "pnl_r": 4.5,
      "hold_bars": 4,
      "component_scores": {
        "kill_zone": 2.0,
        "sweep": 1.9291564380864556,
        "displacement": 0.0,
        "fvg_tap": 2.0,
        "market_structure": 2.0,
        "pd_alignment": 0.0
      }
    },
    {
      "pair": "GBPUSD",
      "direction": "LONG",
      "grade": "A",
      "score": 7.97,
      "session": "London",
      "entry_dt": "2024-01-15 02:00",
      "entry": 1.27618,
      "stop": 1.27,
      "tp1": 1.29472,
      "tp2": 1.31327,
      "atr": 0.0017,
      "outcome": "STOP",
      "exit_price": 1.27448,
      "pnl_r": -1.0,
      "hold_bars": 4,
      "component_scores": {
        "kill_zone": 2.0,
        "sweep": 1.970589561887961,
        "displacement": 2.0,
        "fvg_tap": 0.0,
        "market_structure": 2.0,
        "pd_alignment": 0.0
      }
    },
    {
      "pair": "GBPUSD",
      "direction": "LONG",
      "grade": "A",
      "score": 7.4,
      "session": "London",
      "entry_dt": "2024-01-23 05:00",
      "entry": 1.27108,
      "stop": 1.26662,
      "tp1": 1.28448,
      "tp2": 1.29787,
      "atr": 0.00105,
      "outcome": "STOP",
      "exit_price": 1.27003,
      "pnl_r": -1.0,
      "hold_bars": 3,
      "component_scores": {
        "kill_zone": 2.0,
        "sweep": 1.9043243090167647,
        "displacement": 2.0,
        "fvg_tap": 0.5,
        "market_structure": 2.0,
        "pd_alignment": 0.0
      }
    },
    {
      "pair": "GBPUSD",
      "direction": "SHORT",
      "grade": "A",
      "score": 8.38,
      "session": "London",
      "entry_dt": "2024-01-24 04:00",
      "entry": 1.27097,
      "stop": 1.27207,
      "tp1": 1.26769,
      "tp2": 1.2644,
      "atr": 0.00115,
      "outcome": "STOP",
      "exit_price": 1.27212,
      "pnl_r": -1.0,
      "hold_bars": 2,
      "component_scores": {
        "kill_zone": 2.0,
        "sweep": 1.9027010458520444,
        "displacement": 1.498,
        "fvg_tap": 2.0,
        "market_structure": 0.0,
        "pd_alignment": 0.975268318825046
      }
    },
    {
      "pair": "GBPUSD",
      "direction": "LONG",
      "grade": "A",
      "score": 8.1,
      "session": "London",
      "entry_dt": "2024-01-30 02:00",
      "entry": 1.26999,
      "stop": 1.26726,
      "tp1": 1.2782,
      "tp2": 1.28641,
      "atr": 0.0011,
      "outcome": "STOP",
      "exit_price": 1.2689,
      "pnl_r": -1.0,
      "hold_bars": 1,
      "component_scores": {
        "kill_zone": 2.0,
        "sweep": 2.1008441649087977,
        "displacement": 2.0,
        "fvg_tap": 2.0,
        "market_structure": 0.0,
        "pd_alignment": 0.0
      }
    },
    {
      "pair": "GBPUSD",
      "direction": "SHORT",
      "grade": "A",
      "score": 7.86,
      "session": "London",
      "entry_dt": "2024-02-05 05:00",
      "entry": 1.2621,
      "stop": 1.27684,
      "tp1": 1.21788,
      "tp2": 1.17367,
      "atr": 0.00156,
      "outcome": "TP2",
      "exit_price": 1.25587,
      "pnl_r": 4.5,
      "hold_bars": 5,
      "component_scores": {
        "kill_zone": 2.0,
        "sweep": 1.8638951323150623,
        "displacement": 2.0,
        "fvg_tap": 2.0,
        "market_structure": 0.0,
        "pd_alignment": 0.0
      }
    },
    {
      "pair": "GBPUSD",
      "direction": "SHORT",
      "grade": "A",
      "score": 7.47,
      "session": "London",
      "entry_dt": "2024-02-13 04:00",
      "entry": 1.26175,
      "stop": 1.26422,
      "tp1": 1.25433,
      "tp2": 1.24691,
      "atr": 0.00082,
      "outcome": "STOP",
      "exit_price": 1.26257,
      "pnl_r": -1.0,
      "hold_bars": 2,
      "component_scores": {
        "kill_zone": 2.0,
        "sweep": 1.8742742295667707,
        "displacement": 0.0,
        "fvg_tap": 2.0,
        "market_structure": 1.6,
        "pd_alignment": 0.0
      }
    },
    {
      "pair": "GBPUSD",
      "direction": "SHORT",
      "grade": "A",
      "score": 7.87,
      "session": "London",
      "entry_dt": "2024-02-28 02:00",
      "entry": 1.26709,
      "stop": 1.26971,
      "tp1": 1.25922,
      "tp2": 1.25135,
      "atr": 0.00102,
      "outcome": "TP2",
      "exit_price": 1.26303,
      "pnl_r": 4.5,
      "hold_bars": 6,
      "component_scores": {
        "kill_zone": 2.0,
        "sweep": 1.8691370707367183,
        "displacement": 2.0,
        "fvg_tap": 0.0,
        "market_structure": 2.0,
        "pd_alignment": 0.0
      }
    },
    {
      "pair": "GBPUSD",
      "direction": "SHORT",
      "grade": "A",
      "score": 8.03,
      "session": "London",
      "entry_dt": "2024-03-01 04:00",
      "entry": 1.26381,
      "stop": 1.2674,
      "tp1": 1.25303,
      "tp2": 1.24225,
      "atr": 0.00106,
      "outcome": "STOP",
      "exit_price": 1.26328,
      "pnl_r": -1.0,
      "hold_bars": 7,
      "component_scores": {
        "kill_zone": 2.0,
        "sweep": 2.028423139912013,
        "displacement": 2.0,
        "fvg_tap": 2.0,
        "market_structure": 0.0,
        "pd_alignment": 0.0
      }
    },
    {
      "pair": "GBPUSD",
      "direction": "SHORT",
      "grade": "A",
      "score": 8.37,
      "session": "London",
      "entry_dt": "2024-03-15 03:00",
      "entry": 1.27488,
      "stop": 1.28204,
      "tp1": 1.2534,
      "tp2": 1.23192,
      "atr": 0.00104,
      "outcome": "STOP",
      "exit_price": 1.27592,
      "pnl_r": -1.0,
      "hold_bars": 2,
      "component_scores": {
        "kill_zone": 2.0,
        "sweep": 1.8686034792156605,
        "displacement": 2.0,
        "fvg_tap": 0.5,
        "market_structure": 2.0,
        "pd_alignment": 0.0
      }
    },
    {
      "pair": "GBPUSD",
      "direction": "SHORT",
      "grade": "A",
      "score": 7.9,
      "session": "London",
      "entry_dt": "2024-03-18 04:00",
      "entry": 1.2736,
      "stop": 1.28202,
      "tp1": 1.24835,
      "tp2": 1.2231,
      "atr": 0.00083,
      "outcome": "STOP",
      "exit_price": 1.27443,
      "pnl_r": -1.0,
      "hold_bars": 2,
      "component_scores": {
        "kill_zone": 2.0,
        "sweep": 1.8987330065661703,
        "displacement": 2.0,
        "fvg_tap": 2.0,
        "market_structure": 0.0,
        "pd_alignment": 0.0
      }
    },
    {
      "pair": "GBPUSD",
      "direction": "SHORT",
      "grade": "A",
      "score": 8.32,
      "session": "London",
      "entry_dt": "2024-03-25 04:00",
      "entry": 1.26093,
      "stop": 1.27996,
      "tp1": 1.20383,
      "tp2": 1.14674,
      "atr": 0.00097,
      "outcome": "STOP",
      "exit_price": 1.2619,
      "pnl_r": -1.0,
      "hold_bars": 5,
      "component_scores": {
        "kill_zone": 2.0,
        "sweep": 1.8894968763454558,
        "displacement": 0.0,
        "fvg_tap": 2.0,
        "market_structure": 1.6,
        "pd_alignment": 0.8277328072920209
      }
    },
    {
      "pair": "GBPUSD",
      "direction": "SHORT",
      "grade": "A",
      "score": 7.45,
      "session": "London",
      "entry_dt": "2024-03-28 02:00",
      "entry": 1.26362,
      "stop": 1.2664,
      "tp1": 1.2553,
      "tp2": 1.24697,
      "atr": 0.00099,
      "outcome": "TP2",
      "exit_price": 1.25967,
      "pnl_r": 4.5,
      "hold_bars": 4,
      "component_scores": {
        "kill_zone": 2.0,
        "sweep": 1.9326051556872814,
        "displacement": 2.0,
        "fvg_tap": 0.5,
        "market_structure": 0.0,
        "pd_alignment": 1.0218463107786466
      }
    },
    {
      "pair": "GBPUSD",
      "direction": "LONG",
      "grade": "A",
      "score": 8.2,
      "session": "London",
      "entry_dt": "2024-04-09 02:00",
      "entry": 1.26546,
      "stop": 1.2586,
      "tp1": 1.28605,
      "tp2": 1.30664,
      "atr": 0.00087,
      "outcome": "TP2",
      "exit_price": 1.26895,
      "pnl_r": 4.5,
      "hold_bars": 7,
      "component_scores": {
        "kill_zone": 2.0,
        "sweep": 2.199813762965715,
        "displacement": 2.0,
        "fvg_tap": 2.0,
        "market_structure": 0.0,
        "pd_alignment": 0.0
      }
    },
    {
      "pair": "GBPUSD",
      "direction": "SHORT",
      "grade": "A",
      "score": 8.41,
      "session": "London",
      "entry_dt": "2024-04-15 02:00",
      "entry": 1.24842,
      "stop": 1.25724,
      "tp1": 1.22197,
      "tp2": 1.19552,
      "atr": 0.00134,
      "outcome": "TP2",
      "exit_price": 1.24305,
      "pnl_r": 4.5,
      "hold_bars": 17,
      "component_scores": {
        "kill_zone": 2.0,
        "sweep": 1.9087131214498754,
        "displacement": 2.0,
        "fvg_tap": 0.5,
        "market_structure": 2.0,
        "pd_alignment": 0.0
      }
    },
    {
      "pair": "GBPUSD",
      "direction": "SHORT",
      "grade": "A",
      "score": 8.4,
      "session": "London",
      "entry_dt": "2024-04-16 02:00",
      "entry": 1.24426,
      "stop": 1.24873,
      "tp1": 1.23085,
      "tp2": 1.21744,
      "atr": 0.0013,
      "outcome": "STOP",
      "exit_price": 1.24556,
      "pnl_r": -1.0,
      "hold_bars": 4,
      "component_scores": {
        "kill_zone": 2.0,
        "sweep": 1.9025391352050312,
        "displacement": 2.0,
        "fvg_tap": 0.5,
        "market_structure": 2.0,
        "pd_alignment": 0.0
      }
    },
    {
      "pair": "GBPUSD",
      "direction": "LONG",
      "grade": "A",
      "score": 8.01,
      "session": "London",
      "entry_dt": "2024-04-29 03:00",
      "entry": 1.25194,
      "stop": 1.24583,
      "tp1": 1.27027,
      "tp2": 1.2886,
      "atr": 0.0013,
      "outcome": "TP1",
      "exit_price": 1.25454,
      "pnl_r": 1.25,
      "hold_bars": 20,
      "component_scores": {
        "kill_zone": 2.0,
        "sweep": 2.0138867976406356,
        "displacement": 2.0,
        "fvg_tap": 2.0,
        "market_structure": 0.0,
        "pd_alignment": 0.0
      }
    },
    {
      "pair": "GBPUSD",
      "direction": "LONG",
      "grade": "A",
      "score": 8.39,
      "session": "London",
      "entry_dt": "2024-06-03 02:00",
      "entry": 1.27409,
      "stop": 1.2705,
      "tp1": 1.28484,
      "tp2": 1.2956,
      "atr": 0.0014,
      "outcome": "STOP",
      "exit_price": 1.27269,
      "pnl_r": -1.0,
      "hold_bars": 4,
      "component_scores": {
        "kill_zone": 2.0,
        "sweep": 1.8924832769315827,
        "displacement": 2.0,
        "fvg_tap": 0.5,
        "market_structure": 2.0,
        "pd_alignment": 0.0
      }
    },
    {
      "pair": "GBPUSD",
      "direction": "LONG",
      "grade": "A",
      "score": 8.21,
      "session": "London",
      "entry_dt": "2024-06-04 05:00",
      "entry": 1.28,
      "stop": 1.27043,
      "tp1": 1.30871,
      "tp2": 1.33743,
      "atr": 0.00072,
      "outcome": "STOP",
      "exit_price": 1.27928,
      "pnl_r": -1.0,
      "hold_bars": 1,
      "component_scores": {
        "kill_zone": 2.0,
        "sweep": 2.210704431290239,
        "displacement": 2.0,
        "fvg_tap": 2.0,
        "market_structure": 0.0,
        "pd_alignment": 0.0
      }
    },
    {
      "pair": "GBPUSD",
      "direction": "SHORT",
      "grade": "A",
      "score": 8.32,
      "session": "London",
      "entry_dt": "2024-06-05 03:00",
      "entry": 1.27773,
      "stop": 1.28138,
      "tp1": 1.26676,
      "tp2": 1.25579,
      "atr": 0.00088,
      "outcome": "STOP",
      "exit_price": 1.27861,
      "pnl_r": -1.0,
      "hold_bars": 5,
      "component_scores": {
        "kill_zone": 2.0,
        "sweep": 1.9318238951144284,
        "displacement": 0.0,
        "fvg_tap": 2.0,
        "market_structure": 1.6,
        "pd_alignment": 0.78621830969729
      }
    },
    {
      "pair": "GBPUSD",
      "direction": "LONG",
      "grade": "A",
      "score": 8.04,
      "session": "London",
      "entry_dt": "2024-06-12 02:00",
      "entry": 1.27384,
      "stop": 1.26955,
      "tp1": 1.2867,
      "tp2": 1.29956,
      "atr": 0.00103,
      "outcome": "TP2",
      "exit_price": 1.27795,
      "pnl_r": 4.5,
      "hold_bars": 6,
      "component_scores": {
        "kill_zone": 2.0,
        "sweep": 2.0379005607228935,
        "displacement": 2.0,
        "fvg_tap": 2.0,
        "market_structure": 0.0,
        "pd_alignment": 0.0
      }
    },
    {
      "pair": "GBPUSD",
      "direction": "LONG",
      "grade": "A",
      "score": 7.87,
      "session": "London",
      "entry_dt": "2024-06-19 03:00",
      "entry": 1.27087,
      "stop": 1.26736,
      "tp1": 1.28141,
      "tp2": 1.29195,
      "atr": 0.00083,
      "outcome": "TP1",
      "exit_price": 1.27253,
      "pnl_r": 1.25,
      "hold_bars": 20,
      "component_scores": {
        "kill_zone": 2.0,
        "sweep": 1.8735503487380714,
        "displacement": 2.0,
        "fvg_tap": 0.0,
        "market_structure": 2.0,
        "pd_alignment": 0.0
      }
    },
    {
      "pair": "GBPUSD",
      "direction": "SHORT",
      "grade": "A",
      "score": 7.88,
      "session": "London",
      "entry_dt": "2024-06-21 05:00",
      "entry": 1.26673,
      "stop": 1.27386,
      "tp1": 1.24534,
      "tp2": 1.22396,
      "atr": 0.00066,
      "outcome": "TP2",
      "exit_price": 1.26411,
      "pnl_r": 4.5,
      "hold_bars": 1,
      "component_scores": {
        "kill_zone": 2.0,
        "sweep": 1.8799488065693903,
        "displacement": 2.0,
        "fvg_tap": 2.0,
        "market_structure": 0.0,
        "pd_alignment": 0.0
      }
    },
    {
      "pair": "GBPUSD",
      "direction": "LONG",
      "grade": "A",
      "score": 8.49,
      "session": "London",
      "entry_dt": "2024-06-25 05:00",
      "entry": 1.2683,
      "stop": 1.26309,
      "tp1": 1.28396,
      "tp2": 1.29961,
      "atr": 0.00064,
      "outcome": "STOP",
      "exit_price": 1.26767,
      "pnl_r": -1.0,
      "hold_bars": 1,
      "component_scores": {
        "kill_zone": 2.0,
        "sweep": 1.9936614267794708,
        "displacement": 2.0,
        "fvg_tap": 0.5,
        "market_structure": 2.0,
        "pd_alignment": 0.0
      }
    }
  ]
}